pyprimer/__init__.py
pyprimer/pyprimer.py
pyprimer-0.1.0.dist-info/METADATA
pyprimer-0.1.0.dist-info/WHEEL
pyprimer-0.1.0.dist-info/top_level.txt
pyprimer-0.1.0.dist-info/RECORD
