Metadata-Version: 2.1
Name: pyprimer
Version: 0.1.0
Summary: A simple collection of prime number related functions.
Home-page: https://github.com/mentix02/pyprimer
Author: Manan (mentix02)
Author-email: manan.yadav02@gmail.com
License: UNKNOWN
Platform: UNKNOWN
Classifier: Operating System :: OS Independent
Classifier: Programming Language :: Python :: 3
Classifier: Programming Language :: Python :: 3.7
Classifier: Programming Language :: Python :: 3.8
Classifier: License :: OSI Approved :: MIT License
Classifier: Topic :: Scientific/Engineering :: Mathematics
Requires-Python: >=3.6
